glowseeds/__init__.py
glowseeds/glowseeds.py
glowseeds-0.1.2.dist-info/LICENSE.txt
glowseeds-0.1.2.dist-info/METADATA
glowseeds-0.1.2.dist-info/WHEEL
glowseeds-0.1.2.dist-info/top_level.txt
glowseeds-0.1.2.dist-info/RECORD
