Metadata-Version: 2.1
Name: glowseeds
Version: 0.1.2
Summary: Counting glowing seeds
Home-page: https://github.com/TeamMacLean/glowseeds
Author: Dan MacLean
Author-email: dan.maclean@tsl.ac.uk
License: LICENSE.txt
Platform: UNKNOWN
Requires-Python: >=3.7
Requires-Dist: scikit-image (>=0.18.1)
Requires-Dist: pandas
